{
  "variants": {
    "facing=east,pile=1,slice=1": {
      "model": "bakeries:block/cheese_cocoa_toast_1",
      "y": 90
    },
    "facing=east,pile=1,slice=2": {
      "model": "bakeries:block/cheese_cocoa_toast_2",
      "y": 90
    },
    "facing=east,pile=1,slice=3": {
      "model": "bakeries:block/cheese_cocoa_toast_3",
      "y": 90
    },
    "facing=east,pile=1,slice=4": {
      "model": "bakeries:block/cheese_cocoa_toast_4",
      "y": 90
    },
    "facing=east,pile=2,slice=1": {
      "model": "bakeries:block/cheese_cocoa_toast_pile",
      "y": 90
    },
    "facing=east,pile=2,slice=2": {
      "model": "bakeries:block/cheese_cocoa_toast_pile",
      "y": 90
    },
    "facing=east,pile=2,slice=3": {
      "model": "bakeries:block/cheese_cocoa_toast_pile",
      "y": 90
    },
    "facing=east,pile=2,slice=4": {
      "model": "bakeries:block/cheese_cocoa_toast_pile",
      "y": 90
    },
    "facing=north,pile=1,slice=1": {
      "model": "bakeries:block/cheese_cocoa_toast_1"
    },
    "facing=north,pile=1,slice=2": {
      "model": "bakeries:block/cheese_cocoa_toast_2"
    },
    "facing=north,pile=1,slice=3": {
      "model": "bakeries:block/cheese_cocoa_toast_3"
    },
    "facing=north,pile=1,slice=4": {
      "model": "bakeries:block/cheese_cocoa_toast_4"
    },
    "facing=north,pile=2,slice=1": {
      "model": "bakeries:block/cheese_cocoa_toast_pile"
    },
    "facing=north,pile=2,slice=2": {
      "model": "bakeries:block/cheese_cocoa_toast_pile"
    },
    "facing=north,pile=2,slice=3": {
      "model": "bakeries:block/cheese_cocoa_toast_pile"
    },
    "facing=north,pile=2,slice=4": {
      "model": "bakeries:block/cheese_cocoa_toast_pile"
    },
    "facing=south,pile=1,slice=1": {
      "model": "bakeries:block/cheese_cocoa_toast_1",
      "y": 180
    },
    "facing=south,pile=1,slice=2": {
      "model": "bakeries:block/cheese_cocoa_toast_2",
      "y": 180
    },
    "facing=south,pile=1,slice=3": {
      "model": "bakeries:block/cheese_cocoa_toast_3",
      "y": 180
    },
    "facing=south,pile=1,slice=4": {
      "model": "bakeries:block/cheese_cocoa_toast_4",
      "y": 180
    },
    "facing=south,pile=2,slice=1": {
      "model": "bakeries:block/cheese_cocoa_toast_pile",
      "y": 180
    },
    "facing=south,pile=2,slice=2": {
      "model": "bakeries:block/cheese_cocoa_toast_pile",
      "y": 180
    },
    "facing=south,pile=2,slice=3": {
      "model": "bakeries:block/cheese_cocoa_toast_pile",
      "y": 180
    },
    "facing=south,pile=2,slice=4": {
      "model": "bakeries:block/cheese_cocoa_toast_pile",
      "y": 180
    },
    "facing=west,pile=1,slice=1": {
      "model": "bakeries:block/cheese_cocoa_toast_1",
      "y": 270
    },
    "facing=west,pile=1,slice=2": {
      "model": "bakeries:block/cheese_cocoa_toast_2",
      "y": 270
    },
    "facing=west,pile=1,slice=3": {
      "model": "bakeries:block/cheese_cocoa_toast_3",
      "y": 270
    },
    "facing=west,pile=1,slice=4": {
      "model": "bakeries:block/cheese_cocoa_toast_4",
      "y": 270
    },
    "facing=west,pile=2,slice=1": {
      "model": "bakeries:block/cheese_cocoa_toast_pile",
      "y": 270
    },
    "facing=west,pile=2,slice=2": {
      "model": "bakeries:block/cheese_cocoa_toast_pile",
      "y": 270
    },
    "facing=west,pile=2,slice=3": {
      "model": "bakeries:block/cheese_cocoa_toast_pile",
      "y": 270
    },
    "facing=west,pile=2,slice=4": {
      "model": "bakeries:block/cheese_cocoa_toast_pile",
      "y": 270
    }
  }
}